cyberCore/ConfigSettings.py
cyberCore/CustomLogging.py
cyberCore/Encryption.py
cyberCore/HttpRest.py
cyberCore/PyVersions.py
cyberCore/__about__.py
cyberCore/__init__.py
cyberCore/templates/ConfigSettings.py
cyberCore/templates/Keys.py
cyberCore/templates/__init__.py
cybercore-2025.1.0rc3.dist-info/METADATA
cybercore-2025.1.0rc3.dist-info/WHEEL
cybercore-2025.1.0rc3.dist-info/top_level.txt
cybercore-2025.1.0rc3.dist-info/RECORD
