Metadata-Version: 2.1
Name: cybercore
Version: 2025.1.0rc3
Summary: High-performance secure core framework for scalable, reliable applications
Author-email: Cybernetic Innovations <github@cyberneticinnovations.com>
License: MIT License
Classifier: License :: OSI Approved :: MIT License
Requires-Python: >=3.10
Requires-Dist: PyYAML~=6.0
Requires-Dist: cryptography~=44.0.0
Requires-Dist: loguru~=0.7.3
Requires-Dist: pydantic~=1.10.7
Requires-Dist: requests~=2.32.3
Requires-Dist: urllib3~=2.3.0
Requires-Dist: beautifulsoup4~=4.13.0b2
